README.md
setup.py
rasa_nlu_third/__init__.py
rasa_nlu_third.egg-info/PKG-INFO
rasa_nlu_third.egg-info/SOURCES.txt
rasa_nlu_third.egg-info/dependency_links.txt
rasa_nlu_third.egg-info/top_level.txt
rasa_nlu_third/components/__init__.py
rasa_nlu_third/components/classifiers/__init__.py
rasa_nlu_third/components/classifiers/embedding_intent_classifier_tf.py
rasa_nlu_third/components/extractors/__init__.py
rasa_nlu_third/components/extractors/jieba_pseg_extractor.py
rasa_nlu_third/components/extractors/tf_entity_extractor.py
rasa_nlu_third/components/extractors/triedtree_extractor.py
rasa_nlu_third/data_process/__init__.py
rasa_nlu_third/data_process/classify/__init__.py
rasa_nlu_third/data_process/classify/data_loader.py
rasa_nlu_third/data_process/classify/tf_record_util.py
rasa_nlu_third/data_process/ner/__init__.py
rasa_nlu_third/data_process/ner/data_loader.py
rasa_nlu_third/data_process/ner/tf_record_util.py
rasa_nlu_third/run_local/__init__.py
rasa_nlu_third/run_local/classifiers/__init__.py
rasa_nlu_third/run_local/classifiers/train.py
rasa_nlu_third/run_local/ner/__init__.py
rasa_nlu_third/run_local/ner/train.py
rasa_nlu_third/tf_models/__init__.py
rasa_nlu_third/tf_models/classifiers/__init__.py
rasa_nlu_third/tf_models/classifiers/base_classify_model.py
rasa_nlu_third/tf_models/classifiers/classify_bilstm_model.py
rasa_nlu_third/tf_models/classifiers/constant.py
rasa_nlu_third/tf_models/classifiers/params.py
rasa_nlu_third/tf_models/classifiers/pb_loader.py
rasa_nlu_third/tf_models/ner/__init__.py
rasa_nlu_third/tf_models/ner/base_ner_model.py
rasa_nlu_third/tf_models/ner/bilstm.py
rasa_nlu_third/tf_models/ner/constant.py
rasa_nlu_third/tf_models/ner/params.py
rasa_nlu_third/tf_models/ner/pb_loader.py
rasa_nlu_third/third_models/__init__.py
rasa_nlu_third/third_models/bert/__init__.py
rasa_nlu_third/third_models/bert/create_pretraining_data.py
rasa_nlu_third/third_models/bert/extract_features.py
rasa_nlu_third/third_models/bert/modeling.py
rasa_nlu_third/third_models/bert/modeling_test.py
rasa_nlu_third/third_models/bert/optimization.py
rasa_nlu_third/third_models/bert/optimization_test.py
