Metadata-Version: 1.0
Name: rasa-nlu-third
Version: 0.1.4
Summary: rasa nlu模块扩展
Home-page: https://github.com/fanfanfeng/rasa_nlu_qiu
Author: qiufengfeng
Author-email: 544855237@qq.com
License: LGPL
Platform: UNKNOWN
